swarmauri_llm_leptonai/LeptonAIImgGenModel.py
swarmauri_llm_leptonai/LeptonAIModel.py
swarmauri_llm_leptonai/__init__.py
swarmauri_llm_leptonai-0.7.5.dist-info/LICENSE
swarmauri_llm_leptonai-0.7.5.dist-info/METADATA
swarmauri_llm_leptonai-0.7.5.dist-info/WHEEL
swarmauri_llm_leptonai-0.7.5.dist-info/entry_points.txt
swarmauri_llm_leptonai-0.7.5.dist-info/RECORD
